wnb/__init__.py
wnb/_enum_meta.py
wnb/_utils.py
wnb/dist.py
wnb/gnb.py
wnb/gwnb.py
wnb/typing.py
wnb/stats/__init__.py
wnb/stats/_utils.py
wnb/stats/base.py
wnb/stats/continuous.py
wnb/stats/discrete.py
wnb/stats/enums.py
wnb/stats/typing.py
wnb-0.8.1.dist-info/METADATA
wnb-0.8.1.dist-info/WHEEL
wnb-0.8.1.dist-info/licenses/LICENSE
wnb-0.8.1.dist-info/RECORD
