Metadata-Version: 2.4
Name: wnb
Version: 0.8.1
Summary: Python library for the implementations of general and weighted naive Bayes (WNB) classifiers.
Project-URL: Homepage, https://github.com/msamsami/wnb
Project-URL: Repository, https://github.com/msamsami/wnb
Project-URL: Issues, https://github.com/msamsami/wnb/issues
Author-email: Mehdi Samsami <mehdisamsami@live.com>
License-File: LICENSE
Keywords: bayes,classifier,machine learning,naive bayes,python
Classifier: Intended Audience :: Developers
Classifier: Intended Audience :: Science/Research
Classifier: License :: OSI Approved :: BSD License
Classifier: Programming Language :: Python :: 3.8
Classifier: Programming Language :: Python :: 3.9
Classifier: Programming Language :: Python :: 3.10
Classifier: Programming Language :: Python :: 3.11
Classifier: Programming Language :: Python :: 3.12
Classifier: Programming Language :: Python :: 3.13
Classifier: Topic :: Scientific/Engineering
Classifier: Topic :: Scientific/Engineering :: Artificial Intelligence
Classifier: Topic :: Scientific/Engineering :: Information Analysis
Classifier: Topic :: Software Development :: Libraries :: Python Modules
Requires-Python: <3.14,>=3.8
Requires-Dist: pandas>=1.4.1
Requires-Dist: scikit-learn>=1.0.2
Requires-Dist: scipy>=1.8.0
Requires-Dist: typing-extensions>=4.8.0; python_full_version < '3.11'
